[
  {
    "job": {
      "title": "UI / UX Designer (m/w/d)",
      "company": "Unknown",
      "location": "Remote",
      "url": "https://himalayas.app/companies/teleclinic/jobs/ui-ux-designer-m-w-d",
      "salary": "See posting",
      "description": "Wir wollen digitale \u00e4rztliche Beratung f\u00fcr jeden in Deutschland zug\u00e4nglich machen.",
      "posted_at": "Recently",
      "source": "Himalayas",
      "relevant": true,
      "is_new_grad": false,
      "is_big_tech": false,
      "visa": null
    },
    "remind_at": "2026-07-05T18:55:27.647428-07:00"
  }
]